pubpypack_first_package-0.0.2.dist-info/WHEEL
pubpypack_first_package-0.0.2.dist-info/top_level.txt
pubpypack_first_package-0.0.2.dist-info/LICENSE
pubpypack_first_package-0.0.2.dist-info/METADATA
pubpypack_first_package-0.0.2.dist-info/RECORD
pubpypack_first_package-0.0.2.dist-info/entry_points.txt
imppkg/data.json
imppkg/__init__.py
imppkg/harmonic_mean.c
imppkg/py.typed
imppkg/harmonic_mean.pyx
imppkg/hello.py
imppkg/harmonic_mean.cpython-310-x86_64-linux-gnu.so
imppkg/harmony.py
imppkg/__pycache__/harmonic_mean.cpython-310.pyc
